zaim_sdk/__init__.py
zaim_sdk/get_access_token.py
zaim_sdk/zaim_sdk.py
zaim_sdk-0.0.0.dist-info/LICENSE.txt
zaim_sdk-0.0.0.dist-info/METADATA
zaim_sdk-0.0.0.dist-info/WHEEL
zaim_sdk-0.0.0.dist-info/top_level.txt
zaim_sdk-0.0.0.dist-info/RECORD
