Metadata-Version: 2.1
Name: zaim-sdk
Version: 0.0.0
Summary: Zaim APIのためのPython SDK
Author-email: tra <tisk0711ngm@gmail.com>
Maintainer-email: tra <tisk0711ngm@gmail.com>
License: MIT License
Project-URL: Source, https://github.com/clcl777/zaim-sdk
Classifier: Development Status :: 5 - Production/Stable
Classifier: Intended Audience :: Developers
Classifier: Programming Language :: Python :: 3
Classifier: Environment :: Web Environment
Classifier: License :: OSI Approved :: MIT License
Classifier: Operating System :: OS Independent
Classifier: Typing :: Typed
Classifier: Topic :: Software Development
Requires-Python: >=3.8
License-File: LICENSE.txt
Requires-Dist: Flask >=2.3.3
Requires-Dist: requests-oauthlib >=2.0.0
Requires-Dist: Werkzeug >=2.3.7
Provides-Extra: dev
Requires-Dist: build ; extra == 'dev'
Requires-Dist: twine ; extra == 'dev'
